testwizard/commands_web/AcceptAlertCommand.py
testwizard/commands_web/AddArgumentCommand.py
testwizard/commands_web/AddCapabilityCommand.py
testwizard/commands_web/AddChromeExtensionCommand.py
testwizard/commands_web/AuthenticateUrlCommand.py
testwizard/commands_web/ClearCommand.py
testwizard/commands_web/ClickCommand.py
testwizard/commands_web/CloseWindowCommand.py
testwizard/commands_web/DeleteAllCookiesCommand.py
testwizard/commands_web/DismissAlertCommand.py
testwizard/commands_web/DragNDropCommand.py
testwizard/commands_web/ExitFullScreenCommand.py
testwizard/commands_web/GetChildrenCommand.py
testwizard/commands_web/GetChildrenResult.py
testwizard/commands_web/GetCurrentWindowHandleCommand.py
testwizard/commands_web/GetCurrentWindowHandleResult.py
testwizard/commands_web/GetElementAttributeCommand.py
testwizard/commands_web/GetElementAttributeResult.py
testwizard/commands_web/GetElementCommand.py
testwizard/commands_web/GetElementResult.py
testwizard/commands_web/GetUrlCommand.py
testwizard/commands_web/GetUrlResult.py
testwizard/commands_web/GetWindowHandlesCommand.py
testwizard/commands_web/GetWindowHandlesResult.py
testwizard/commands_web/GoToUrlCommand.py
testwizard/commands_web/IsDriverLoadedCommand.py
testwizard/commands_web/MaximizeWindowCommand.py
testwizard/commands_web/MultiAction_ClickAndHoldCommand.py
testwizard/commands_web/MultiAction_ClickCommand.py
testwizard/commands_web/MultiAction_ContextClickCommand.py
testwizard/commands_web/MultiAction_DoubleClickCommand.py
testwizard/commands_web/MultiAction_DragAndDropCommand.py
testwizard/commands_web/MultiAction_DragAndDropToOffsetCommand.py
testwizard/commands_web/MultiAction_MoveToElementCommand.py
testwizard/commands_web/MultiAction_MoveToElementOffsetCommand.py
testwizard/commands_web/MultiAction_NewCommand.py
testwizard/commands_web/MultiAction_PerformCommand.py
testwizard/commands_web/MultiAction_ReleaseCommand.py
testwizard/commands_web/MultiAction_SendKeysCommand.py
testwizard.commands_web-3.8.1.dist-info/LICENSE.txt
testwizard.commands_web-3.8.1.dist-info/METADATA
testwizard.commands_web-3.8.1.dist-info/WHEEL
testwizard.commands_web-3.8.1.dist-info/top_level.txt
testwizard.commands_web-3.8.1.dist-info/RECORD
